{
"frames": {
	"fire_ball.0001.png": {
		"frame": {"x":572, "y":681, "w":142, "h":302},
		"spriteSourceSize": {"x":953,"y":426,"w":2048,"h":1152},
		"sourceSize": {"w":2048,"h":1152}
	},
	"fire_ball.0002.png": {
		"frame": {"x":715, "y":0, "w":142, "h":316},
		"spriteSourceSize": {"x":953,"y":412,"w":2048,"h":1152},
		"sourceSize": {"w":2048,"h":1152}
	},
	"fire_ball.0003.png": {
		"frame": {"x":572, "y":340, "w":142, "h":340},
		"spriteSourceSize": {"x":953,"y":388,"w":2048,"h":1152},
		"sourceSize": {"w":2048,"h":1152}
	},
	"fire_ball.0004.png": {
		"frame": {"x":572, "y":0, "w":142, "h":339},
		"spriteSourceSize": {"x":953,"y":389,"w":2048,"h":1152},
		"sourceSize": {"w":2048,"h":1152}
	},
	"fire_ball.0005.png": {
		"frame": {"x":429, "y":684, "w":142, "h":296},
		"spriteSourceSize": {"x":953,"y":432,"w":2048,"h":1152},
		"sourceSize": {"w":2048,"h":1152}
	},
	"fire_ball.0006.png": {
		"frame": {"x":715, "y":649, "w":142, "h":340},
		"spriteSourceSize": {"x":953,"y":388,"w":2048,"h":1152},
		"sourceSize": {"w":2048,"h":1152}
	},
	"fire_ball.0007.png": {
		"frame": {"x":429, "y":0, "w":142, "h":334},
		"spriteSourceSize": {"x":953,"y":394,"w":2048,"h":1152},
		"sourceSize": {"w":2048,"h":1152}
	},
	"fire_ball.0008.png": {
		"frame": {"x":286, "y":365, "w":142, "h":391},
		"spriteSourceSize": {"x":953,"y":337,"w":2048,"h":1152},
		"sourceSize": {"w":2048,"h":1152}
	},
	"fire_ball.0009.png": {
		"frame": {"x":286, "y":0, "w":142, "h":364},
		"spriteSourceSize": {"x":953,"y":364,"w":2048,"h":1152},
		"sourceSize": {"w":2048,"h":1152}
	},
	"fire_ball.0010.png": {
		"frame": {"x":143, "y":363, "w":142, "h":332},
		"spriteSourceSize": {"x":953,"y":396,"w":2048,"h":1152},
		"sourceSize": {"w":2048,"h":1152}
	},
	"fire_ball.0011.png": {
		"frame": {"x":143, "y":0, "w":142, "h":362},
		"spriteSourceSize": {"x":953,"y":366,"w":2048,"h":1152},
		"sourceSize": {"w":2048,"h":1152}
	},
	"fire_ball.0012.png": {
		"frame": {"x":0, "y":339, "w":142, "h":378},
		"spriteSourceSize": {"x":953,"y":350,"w":2048,"h":1152},
		"sourceSize": {"w":2048,"h":1152}
	},
	"fire_ball.0013.png": {
		"frame": {"x":0, "y":0, "w":142, "h":338},
		"spriteSourceSize": {"x":953,"y":390,"w":2048,"h":1152},
		"sourceSize": {"w":2048,"h":1152}
	},
	"fire_ball.0014.png": {
		"frame": {"x":429, "y":335, "w":142, "h":348},
		"spriteSourceSize": {"x":953,"y":380,"w":2048,"h":1152},
		"sourceSize": {"w":2048,"h":1152}
	},
	"fire_ball.0015.png": {
		"frame": {"x":715, "y":317, "w":142, "h":331},
		"spriteSourceSize": {"x":953,"y":397,"w":2048,"h":1152},
		"sourceSize": {"w":2048,"h":1152}
	}

},
"meta": {
	"image": "fireSprites.png",
	"size": {"w": 858, "h": 990},
	"scale": "1"
}
}